<Properties StartupConfiguration="{53BCE6AB-18F9-024E-6385-E8A32AE749D4}|">
  <MonoDevelop.Ide.Workbench ActiveDocument="Assets/Scripts/StopSpawningPowerup.cs">
    <Files>
      <File FileName="Assets/Scripts/EnemySpawner.cs" Line="67" Column="41" />
      <File FileName="Assets/Scripts/StopSpawningPowerup.cs" Line="48" Column="6" />
      <File FileName="Assets/Scripts/TextPopup.cs" Line="66" Column="1" />
    </Files>
  </MonoDevelop.Ide.Workbench>
  <MonoDevelop.Ide.DebuggingService.PinnedWatches />
  <MonoDevelop.Ide.Workspace ActiveConfiguration="Debug" />
  <MonoDevelop.Ide.ItemProperties.Assembly-CSharp PreferredExecutionTarget="Unity.Editor" />
  <MonoDevelop.Ide.DebuggingService.Breakpoints>
    <BreakpointStore />
  </MonoDevelop.Ide.DebuggingService.Breakpoints>
  <MultiItemStartupConfigurations />
</Properties>