{
"instructions_readme": "1) Open Chrome, 2) go to chrome://tracing, 3) click Load, 4) navigate to this file.",

"traceEvents":[
{ "pid": 1, "tid": 1, "ph": "M", "name": "thread_name", "args": { "name": "" } },
{ "pid": 1, "tid": 1, "ts": 2.00299988500774, "dur": 11552489.2578125, "ph": "X", "name": "il2cpp.exe", "args": { "durationMS": 11552.4892578125, "detail": "" } },
{ "pid": 1, "tid": 1, "ts": 259147.857666016, "dur": 11292144.53125, "ph": "X", "name": "ConvertAssemblies", "args": { "durationMS": 11292.14453125, "detail": "" } },
{ "pid": 1, "tid": 1, "ts": 289268.402099609, "dur": 73252.6473999023, "ph": "X", "name": "Collect assemblies to convert", "args": { "durationMS": 73.2526473999023, "detail": "" } },
{ "pid": 1, "tid": 1, "ts": 362687.896728516, "dur": 76698.6846923828, "ph": "X", "name": "RegisterCorlib", "args": { "durationMS": 76.6986846923828, "detail": "" } },
{ "pid": 1, "tid": 1, "ts": 439687.072753906, "dur": 69161.5676879883, "ph": "X", "name": "PreProcessIL", "args": { "durationMS": 69.1615676879883, "detail": "" } },
{ "pid": 1, "tid": 1, "ts": 439687.408447266, "dur": 19692.1329498291, "ph": "X", "name": "Inject base types and finalizers into COM and Windows Runtime types", "args": { "durationMS": 19.6921329498291, "detail": "" } },
{ "pid": 1, "tid": 1, "ts": 440010.803222656, "dur": 12873.2929229736, "ph": "X", "name": "ModifyCOMAndWindowsRuntimeTypes in assembly", "args": { "durationMS": 12.8732929229736, "detail": "mscorlib" } },
{ "pid": 1, "tid": 1, "ts": 452886.047363281, "dur": 2678.65180969238, "ph": "X", "name": "ModifyCOMAndWindowsRuntimeTypes in assembly", "args": { "durationMS": 2.67865180969238, "detail": "System.Configuration" } },
{ "pid": 1, "tid": 1, "ts": 456207.855224609, "dur": 1392.24207401276, "ph": "X", "name": "ModifyCOMAndWindowsRuntimeTypes in assembly", "args": { "durationMS": 1.39224207401276, "detail": "UnityEngine.CoreModule" } },
{ "pid": 1, "tid": 1, "ts": 457887.664794922, "dur": 1330.87599277496, "ph": "X", "name": "ModifyCOMAndWindowsRuntimeTypes in assembly", "args": { "durationMS": 1.33087599277496, "detail": "UnityEngine.UI" } },
{ "pid": 1, "tid": 1, "ts": 459379.699707031, "dur": 49467.1516418457, "ph": "X", "name": "ApplyDefaultMarshalAsAttribute", "args": { "durationMS": 49.4671516418457, "detail": "" } },
{ "pid": 1, "tid": 1, "ts": 459722.747802734, "dur": 33776.1764526367, "ph": "X", "name": "ApplyDefaultMarshalAsAttributeVisitor in assembly", "args": { "durationMS": 33.7761764526367, "detail": "mscorlib" } },
{ "pid": 1, "tid": 1, "ts": 493568.420410156, "dur": 9355.42678833008, "ph": "X", "name": "ApplyDefaultMarshalAsAttributeVisitor in assembly", "args": { "durationMS": 9.35542678833008, "detail": "System" } },
{ "pid": 1, "tid": 1, "ts": 503150.360107422, "dur": 1554.21507358551, "ph": "X", "name": "ApplyDefaultMarshalAsAttributeVisitor in assembly", "args": { "durationMS": 1.55421507358551, "detail": "UnityEngine.CoreModule" } },
{ "pid": 1, "tid": 1, "ts": 505735.870361328, "dur": 1778.74302864075, "ph": "X", "name": "ApplyDefaultMarshalAsAttributeVisitor in assembly", "args": { "durationMS": 1.77874302864075, "detail": "UnityEngine.UI" } },
{ "pid": 1, "tid": 1, "ts": 507515.838623047, "dur": 1328.29797267914, "ph": "X", "name": "ApplyDefaultMarshalAsAttributeVisitor in assembly", "args": { "durationMS": 1.32829797267914, "detail": "Assembly-CSharp" } },
{ "pid": 1, "tid": 1, "ts": 509016.906738281, "dur": 9367.91324615479, "ph": "X", "name": "WriteResources", "args": { "durationMS": 9.36791324615479, "detail": "" } },
{ "pid": 1, "tid": 1, "ts": 518675.354003906, "dur": 38328.8841247559, "ph": "X", "name": "CopyEtcFolder", "args": { "durationMS": 38.3288841247559, "detail": "" } },
{ "pid": 1, "tid": 1, "ts": 557553.833007813, "dur": 271294.891357422, "ph": "X", "name": "PreProcessStage", "args": { "durationMS": 271.294891357422, "detail": "" } },
{ "pid": 1, "tid": 1, "ts": 828856.323242188, "dur": 2549.3860244751, "ph": "X", "name": "Debugger Sequence Points", "args": { "durationMS": 2.5493860244751, "detail": "" } },
{ "pid": 1, "tid": 1, "ts": 832166.625976563, "dur": 1213594.84863281, "ph": "X", "name": "Generics Collection", "args": { "durationMS": 1213.59484863281, "detail": "" } },
{ "pid": 1, "tid": 1, "ts": 832166.809082031, "dur": 1203479.4921875, "ph": "X", "name": "GenericsCollector.Collect", "args": { "durationMS": 1203.4794921875, "detail": "" } },
{ "pid": 1, "tid": 1, "ts": 2035646.85058594, "dur": 7922.08385467529, "ph": "X", "name": "CollectGenericVirtualMethods.Collect", "args": { "durationMS": 7.92208385467529, "detail": "" } },
{ "pid": 1, "tid": 1, "ts": 2043569.3359375, "dur": 1536.19205951691, "ph": "X", "name": "AddExtraTypes", "args": { "durationMS": 1.53619205951691, "detail": "" } },
{ "pid": 1, "tid": 1, "ts": 2045761.84082031, "dur": 1715.7130241394, "ph": "X", "name": "Add Windows Runtime type names", "args": { "durationMS": 1.7157130241394, "detail": "" } },
{ "pid": 1, "tid": 1, "ts": 2045762.08496094, "dur": 1715.00301361084, "ph": "X", "name": "Add Windows Runtime type names", "args": { "durationMS": 1.71500301361084, "detail": "" } },
{ "pid": 1, "tid": 1, "ts": 2058858.15429688, "dur": 5151350.09765625, "ph": "X", "name": "AllAssemblyConversion", "args": { "durationMS": 5151.35009765625, "detail": "" } },
{ "pid": 1, "tid": 1, "ts": 2066209.22851563, "dur": 2833446.77734375, "ph": "X", "name": "Convert", "args": { "durationMS": 2833.44677734375, "detail": "mscorlib" } },
{ "pid": 1, "tid": 1, "ts": 2066210.9375, "dur": 2833444.58007813, "ph": "X", "name": "Code", "args": { "durationMS": 2833.44458007813, "detail": "" } },
{ "pid": 1, "tid": 1, "ts": 2066881.10351563, "dur": 2832773.92578125, "ph": "X", "name": "Methods", "args": { "durationMS": 2832.77392578125, "detail": "Definitions" } },
{ "pid": 1, "tid": 1, "ts": 4903651.85546875, "dur": 4075.96397399902, "ph": "X", "name": "Convert", "args": { "durationMS": 4.07596397399902, "detail": "System.Configuration" } },
{ "pid": 1, "tid": 1, "ts": 4903653.80859375, "dur": 4074.19919967651, "ph": "X", "name": "Code", "args": { "durationMS": 4.07419919967651, "detail": "" } },
{ "pid": 1, "tid": 1, "ts": 4903665.52734375, "dur": 4061.45572662354, "ph": "X", "name": "Methods", "args": { "durationMS": 4.06145572662354, "detail": "Definitions" } },
{ "pid": 1, "tid": 1, "ts": 4911719.7265625, "dur": 3365.45300483704, "ph": "X", "name": "Convert", "args": { "durationMS": 3.36545300483704, "detail": "System.Xml" } },
{ "pid": 1, "tid": 1, "ts": 4911721.19140625, "dur": 3363.78812789917, "ph": "X", "name": "Code", "args": { "durationMS": 3.36378812789917, "detail": "" } },
{ "pid": 1, "tid": 1, "ts": 4911728.515625, "dur": 3355.85308074951, "ph": "X", "name": "Methods", "args": { "durationMS": 3.35585308074951, "detail": "Definitions" } },
{ "pid": 1, "tid": 1, "ts": 4918859.375, "dur": 328318.298339844, "ph": "X", "name": "Convert", "args": { "durationMS": 328.318298339844, "detail": "System" } },
{ "pid": 1, "tid": 1, "ts": 4918861.328125, "dur": 328316.589355469, "ph": "X", "name": "Code", "args": { "durationMS": 328.316589355469, "detail": "" } },
{ "pid": 1, "tid": 1, "ts": 4918894.53125, "dur": 328282.775878906, "ph": "X", "name": "Methods", "args": { "durationMS": 328.282775878906, "detail": "Definitions" } },
{ "pid": 1, "tid": 1, "ts": 5252109.375, "dur": 11199.7222900391, "ph": "X", "name": "Convert", "args": { "durationMS": 11.1997222900391, "detail": "Mono.Security" } },
{ "pid": 1, "tid": 1, "ts": 5252114.2578125, "dur": 11195.0016021729, "ph": "X", "name": "Code", "args": { "durationMS": 11.1950016021729, "detail": "" } },
{ "pid": 1, "tid": 1, "ts": 5252127.44140625, "dur": 11181.8876266479, "ph": "X", "name": "Methods", "args": { "durationMS": 11.1818876266479, "detail": "Definitions" } },
{ "pid": 1, "tid": 1, "ts": 5268458.0078125, "dur": 1006.38902187347, "ph": "X", "name": "Convert", "args": { "durationMS": 1.00638902187347, "detail": "System.Core" } },
{ "pid": 1, "tid": 1, "ts": 5268459.47265625, "dur": 1004.40907478333, "ph": "X", "name": "Code", "args": { "durationMS": 1.00440907478333, "detail": "" } },
{ "pid": 1, "tid": 1, "ts": 5268467.28515625, "dur": 996.361017227173, "ph": "X", "name": "Methods", "args": { "durationMS": 0.996361017227173, "detail": "Definitions" } },
{ "pid": 1, "tid": 1, "ts": 5274729.4921875, "dur": 17290.5178070068, "ph": "X", "name": "Convert", "args": { "durationMS": 17.2905178070068, "detail": "UnityEngine.SharedInternalsModule" } },
{ "pid": 1, "tid": 1, "ts": 5274731.93359375, "dur": 17287.8894805908, "ph": "X", "name": "Code", "args": { "durationMS": 17.2878894805908, "detail": "" } },
{ "pid": 1, "tid": 1, "ts": 5274757.8125, "dur": 17261.6348266602, "ph": "X", "name": "Methods", "args": { "durationMS": 17.2616348266602, "detail": "Definitions" } },
{ "pid": 1, "tid": 1, "ts": 5296460.44921875, "dur": 377986.511230469, "ph": "X", "name": "Convert", "args": { "durationMS": 377.986511230469, "detail": "UnityEngine.CoreModule" } },
{ "pid": 1, "tid": 1, "ts": 5296462.40234375, "dur": 377984.527587891, "ph": "X", "name": "Code", "args": { "durationMS": 377.984527587891, "detail": "" } },
{ "pid": 1, "tid": 1, "ts": 5296578.125, "dur": 377868.530273438, "ph": "X", "name": "Methods", "args": { "durationMS": 377.868530273438, "detail": "Definitions" } },
{ "pid": 1, "tid": 1, "ts": 5680044.921875, "dur": 1169.21806335449, "ph": "X", "name": "Convert", "args": { "durationMS": 1.16921806335449, "detail": "UnityEngine.GridModule" } },
{ "pid": 1, "tid": 1, "ts": 5680047.36328125, "dur": 1166.25106334686, "ph": "X", "name": "Code", "args": { "durationMS": 1.16625106334686, "detail": "" } },
{ "pid": 1, "tid": 1, "ts": 5680054.19921875, "dur": 1159.38496589661, "ph": "X", "name": "Methods", "args": { "durationMS": 1.15938496589661, "detail": "Definitions" } },
{ "pid": 1, "tid": 1, "ts": 5686520.99609375, "dur": 18349.5216369629, "ph": "X", "name": "Convert", "args": { "durationMS": 18.3495216369629, "detail": "UnityEngine.Physics2DModule" } },
{ "pid": 1, "tid": 1, "ts": 5686522.94921875, "dur": 18347.1240997314, "ph": "X", "name": "Code", "args": { "durationMS": 18.3471240997314, "detail": "" } },
{ "pid": 1, "tid": 1, "ts": 5686530.76171875, "dur": 18338.8786315918, "ph": "X", "name": "Methods", "args": { "durationMS": 18.3388786315918, "detail": "Definitions" } },
{ "pid": 1, "tid": 1, "ts": 5708633.30078125, "dur": 18519.8040008545, "ph": "X", "name": "Convert", "args": { "durationMS": 18.5198040008545, "detail": "UnityEngine.TextRenderingModule" } },
{ "pid": 1, "tid": 1, "ts": 5708635.25390625, "dur": 18517.650604248, "ph": "X", "name": "Code", "args": { "durationMS": 18.517650604248, "detail": "" } },
{ "pid": 1, "tid": 1, "ts": 5708669.43359375, "dur": 18483.2077026367, "ph": "X", "name": "Methods", "args": { "durationMS": 18.4832077026367, "detail": "Definitions" } },
{ "pid": 1, "tid": 1, "ts": 5733877.9296875, "dur": 23736.8106842041, "ph": "X", "name": "Convert", "args": { "durationMS": 23.7368106842041, "detail": "UnityEngine.AnimationModule" } },
{ "pid": 1, "tid": 1, "ts": 5733880.859375, "dur": 23733.491897583, "ph": "X", "name": "Code", "args": { "durationMS": 23.733491897583, "detail": "" } },
{ "pid": 1, "tid": 1, "ts": 5733906.25, "dur": 23707.914352417, "ph": "X", "name": "Methods", "args": { "durationMS": 23.707914352417, "detail": "Definitions" } },
{ "pid": 1, "tid": 1, "ts": 5761393.06640625, "dur": 9102.04601287842, "ph": "X", "name": "Convert", "args": { "durationMS": 9.10204601287842, "detail": "UnityEngine.AudioModule" } },
{ "pid": 1, "tid": 1, "ts": 5761394.53125, "dur": 9100.23307800293, "ph": "X", "name": "Code", "args": { "durationMS": 9.10023307800293, "detail": "" } },
{ "pid": 1, "tid": 1, "ts": 5761403.80859375, "dur": 9090.86227416992, "ph": "X", "name": "Methods", "args": { "durationMS": 9.09086227416992, "detail": "Definitions" } },
{ "pid": 1, "tid": 1, "ts": 5776026.3671875, "dur": 36307.5790405273, "ph": "X", "name": "Convert", "args": { "durationMS": 36.3075790405273, "detail": "UnityEngine.GameCenterModule" } },
{ "pid": 1, "tid": 1, "ts": 5776028.3203125, "dur": 36304.8515319824, "ph": "X", "name": "Code", "args": { "durationMS": 36.3048515319824, "detail": "" } },
{ "pid": 1, "tid": 1, "ts": 5776052.24609375, "dur": 36280.7846069336, "ph": "X", "name": "Methods", "args": { "durationMS": 36.2807846069336, "detail": "Definitions" } },
{ "pid": 1, "tid": 1, "ts": 5816045.8984375, "dur": 78667.48046875, "ph": "X", "name": "Convert", "args": { "durationMS": 78.66748046875, "detail": "UnityEngine.IMGUIModule" } },
{ "pid": 1, "tid": 1, "ts": 5816047.36328125, "dur": 78665.2221679688, "ph": "X", "name": "Code", "args": { "durationMS": 78.6652221679688, "detail": "" } },
{ "pid": 1, "tid": 1, "ts": 5816059.08203125, "dur": 78653.2745361328, "ph": "X", "name": "Methods", "args": { "durationMS": 78.6532745361328, "detail": "Definitions" } },
{ "pid": 1, "tid": 1, "ts": 5898572.265625, "dur": 1080.37507534027, "ph": "X", "name": "Convert", "args": { "durationMS": 1.08037507534027, "detail": "UnityEngine.ImageConversionModule" } },
{ "pid": 1, "tid": 1, "ts": 5898575.1953125, "dur": 1077.800989151, "ph": "X", "name": "Code", "args": { "durationMS": 1.077800989151, "detail": "" } },
{ "pid": 1, "tid": 1, "ts": 5898578.61328125, "dur": 1072.96097278595, "ph": "X", "name": "Methods", "args": { "durationMS": 1.07296097278595, "detail": "Definitions" } },
{ "pid": 1, "tid": 1, "ts": 5903640.625, "dur": 15663.1088256836, "ph": "X", "name": "Convert", "args": { "durationMS": 15.6631088256836, "detail": "UnityEngine.PhysicsModule" } },
{ "pid": 1, "tid": 1, "ts": 5903642.08984375, "dur": 15661.057472229, "ph": "X", "name": "Code", "args": { "durationMS": 15.661057472229, "detail": "" } },
{ "pid": 1, "tid": 1, "ts": 5903649.4140625, "dur": 15652.9455184937, "ph": "X", "name": "Methods", "args": { "durationMS": 15.6529455184937, "detail": "Definitions" } },
{ "pid": 1, "tid": 1, "ts": 5924792.48046875, "dur": 9110.47267913818, "ph": "X", "name": "Convert", "args": { "durationMS": 9.11047267913818, "detail": "UnityEngine.TilemapModule" } },
{ "pid": 1, "tid": 1, "ts": 5924794.43359375, "dur": 9107.741355896, "ph": "X", "name": "Code", "args": { "durationMS": 9.107741355896, "detail": "" } },
{ "pid": 1, "tid": 1, "ts": 5924806.15234375, "dur": 9096.10557556152, "ph": "X", "name": "Methods", "args": { "durationMS": 9.09610557556152, "detail": "Definitions" } },
{ "pid": 1, "tid": 1, "ts": 5937984.86328125, "dur": 13223.087310791, "ph": "X", "name": "Convert", "args": { "durationMS": 13.223087310791, "detail": "UnityEngine.UIModule" } },
{ "pid": 1, "tid": 1, "ts": 5937986.81640625, "dur": 13221.3296890259, "ph": "X", "name": "Code", "args": { "durationMS": 13.2213296890259, "detail": "" } },
{ "pid": 1, "tid": 1, "ts": 5937993.65234375, "dur": 13213.6163711548, "ph": "X", "name": "Methods", "args": { "durationMS": 13.2136163711548, "detail": "Definitions" } },
{ "pid": 1, "tid": 1, "ts": 5954800.78125, "dur": 4779.72459793091, "ph": "X", "name": "Convert", "args": { "durationMS": 4.77972459793091, "detail": "UnityEngine.UnityAnalyticsModule" } },
{ "pid": 1, "tid": 1, "ts": 5954802.24609375, "dur": 4777.8468132019, "ph": "X", "name": "Code", "args": { "durationMS": 4.7778468132019, "detail": "" } },
{ "pid": 1, "tid": 1, "ts": 5954808.59375, "dur": 4771.53873443604, "ph": "X", "name": "Methods", "args": { "durationMS": 4.77153873443604, "detail": "Definitions" } },
{ "pid": 1, "tid": 1, "ts": 5963042.48046875, "dur": 3114.43614959717, "ph": "X", "name": "Convert", "args": { "durationMS": 3.11443614959717, "detail": "UnityEngine.UnityWebRequestModule" } },
{ "pid": 1, "tid": 1, "ts": 5963043.9453125, "dur": 3112.28585243225, "ph": "X", "name": "Code", "args": { "durationMS": 3.11228585243225, "detail": "" } },
{ "pid": 1, "tid": 1, "ts": 5963048.33984375, "dur": 3107.18321800232, "ph": "X", "name": "Methods", "args": { "durationMS": 3.10718321800232, "detail": "Definitions" } },
{ "pid": 1, "tid": 1, "ts": 5970516.6015625, "dur": 528.51802110672, "ph": "X", "name": "Convert", "args": { "durationMS": 0.52851802110672, "detail": "UnityEngine" } },
{ "pid": 1, "tid": 1, "ts": 5970519.53125, "dur": 525.72101354599, "ph": "X", "name": "Code", "args": { "durationMS": 0.52572101354599, "detail": "" } },
{ "pid": 1, "tid": 1, "ts": 5970525.390625, "dur": 519.591987133026, "ph": "X", "name": "Methods", "args": { "durationMS": 0.519591987133026, "detail": "Definitions" } },
{ "pid": 1, "tid": 1, "ts": 5977338.37890625, "dur": 914967.163085938, "ph": "X", "name": "Convert", "args": { "durationMS": 914.967163085938, "detail": "UnityEngine.UI" } },
{ "pid": 1, "tid": 1, "ts": 5977341.30859375, "dur": 914964.172363281, "ph": "X", "name": "Code", "args": { "durationMS": 914.964172363281, "detail": "" } },
{ "pid": 1, "tid": 1, "ts": 5977437.5, "dur": 914868.103027344, "ph": "X", "name": "Methods", "args": { "durationMS": 914.868103027344, "detail": "Definitions" } },
{ "pid": 1, "tid": 1, "ts": 6896177.24609375, "dur": 314013.061523438, "ph": "X", "name": "Convert", "args": { "durationMS": 314.013061523438, "detail": "Assembly-CSharp" } },
{ "pid": 1, "tid": 1, "ts": 6896178.7109375, "dur": 314011.260986328, "ph": "X", "name": "Code", "args": { "durationMS": 314.011260986328, "detail": "" } },
{ "pid": 1, "tid": 1, "ts": 6896221.19140625, "dur": 313966.583251953, "ph": "X", "name": "Methods", "args": { "durationMS": 313.966583251953, "detail": "Definitions" } },
{ "pid": 1, "tid": 1, "ts": 7210209.47265625, "dur": 2407280.51757813, "ph": "X", "name": "WriteGenerics", "args": { "durationMS": 2407.28051757813, "detail": "" } },
{ "pid": 1, "tid": 1, "ts": 7222890.13671875, "dur": 22138.8683319092, "ph": "X", "name": "Arrays Definitions", "args": { "durationMS": 22.1388683319092, "detail": "" } },
{ "pid": 1, "tid": 1, "ts": 7245491.69921875, "dur": 445735.931396484, "ph": "X", "name": "GenericInstanceMethods", "args": { "durationMS": 445.735931396484, "detail": "" } },
{ "pid": 1, "tid": 1, "ts": 7691228.515625, "dur": 1696595.82519531, "ph": "X", "name": "GenericInstanceTypes", "args": { "durationMS": 1696.59582519531, "detail": "" } },
{ "pid": 1, "tid": 1, "ts": 9388258.7890625, "dur": 229219.940185547, "ph": "X", "name": "GenericComDefinitions", "args": { "durationMS": 229.219940185547, "detail": "" } },
{ "pid": 1, "tid": 1, "ts": 9627420.8984375, "dur": 260659.057617188, "ph": "X", "name": "MetadataCollector", "args": { "durationMS": 260.659057617188, "detail": "" } },
{ "pid": 1, "tid": 1, "ts": 9630913.0859375, "dur": 10576.5924453735, "ph": "X", "name": "UpdateEmptyTokens", "args": { "durationMS": 10.5765924453735, "detail": "" } },
{ "pid": 1, "tid": 1, "ts": 9643773.4375, "dur": 11192.6507949829, "ph": "X", "name": "ValidateTokens", "args": { "durationMS": 11.1926507949829, "detail": "" } },
{ "pid": 1, "tid": 1, "ts": 9888444.3359375, "dur": 2292.34600067139, "ph": "X", "name": "Write COM Callable Wrappers", "args": { "durationMS": 2.29234600067139, "detail": "" } },
{ "pid": 1, "tid": 1, "ts": 9890309.5703125, "dur": 424.663007259369, "ph": "X", "name": "Collect implemented projected interfaces by COM Callable Wrappers", "args": { "durationMS": 0.424663007259369, "detail": "" } },
{ "pid": 1, "tid": 1, "ts": 9890737.3046875, "dur": 1657493.53027344, "ph": "X", "name": "Metadata", "args": { "durationMS": 1657.49353027344, "detail": "Global" } },
{ "pid": 1, "tid": 1, "ts": 9933816.40625, "dur": 383150.177001953, "ph": "X", "name": "Attributes", "args": { "durationMS": 383.150177001953, "detail": "" } },
{ "pid": 1, "tid": 1, "ts": 10435732.421875, "dur": 255978.424072266, "ph": "X", "name": "WriteCodeRegistration", "args": { "durationMS": 255.978424072266, "detail": "" } },
{ "pid": 1, "tid": 1, "ts": 10488900.390625, "dur": 5245.79477310181, "ph": "X", "name": "GenericContextCollector", "args": { "durationMS": 5.24579477310181, "detail": "Collect" } },
{ "pid": 1, "tid": 1, "ts": 10550208.0078125, "dur": 4451.73215866089, "ph": "X", "name": "ReversePInvokerWrapperTable", "args": { "durationMS": 4.45173215866089, "detail": "Il2CppReversePInvokeWrapperTable.cpp" } },
{ "pid": 1, "tid": 1, "ts": 10555114.2578125, "dur": 62964.3440246582, "ph": "X", "name": "GenericMethodPointerTable", "args": { "durationMS": 62.9643440246582, "detail": "Il2CppGenericMethodPointerTable.cpp" } },
{ "pid": 1, "tid": 1, "ts": 10618452.1484375, "dur": 57487.4382019043, "ph": "X", "name": "InvokerTable", "args": { "durationMS": 57.4874382019043, "detail": "Il2CppInvokerTable.cpp" } },
{ "pid": 1, "tid": 1, "ts": 10677435.546875, "dur": 9945.81699371338, "ph": "X", "name": "InteropDataTable", "args": { "durationMS": 9.94581699371338, "detail": "Il2CppInteropDataTable.cpp" } },
{ "pid": 1, "tid": 1, "ts": 10691710.9375, "dur": 856518.676757813, "ph": "X", "name": "WriteMetadata", "args": { "durationMS": 856.518676757813, "detail": "" } },
{ "pid": 1, "tid": 1, "ts": 10769255.859375, "dur": 4179.00705337524, "ph": "X", "name": "Metadata", "args": { "durationMS": 4.17900705337524, "detail": "Collect string literals" } },
{ "pid": 1, "tid": 1, "ts": 10873050.78125, "dur": 69200.2334594727, "ph": "X", "name": "GenericClasses", "args": { "durationMS": 69.2002334594727, "detail": "" } },
{ "pid": 1, "tid": 1, "ts": 10942250.9765625, "dur": 16886.7683410645, "ph": "X", "name": "GenericInst2", "args": { "durationMS": 16.8867683410645, "detail": "" } },
{ "pid": 1, "tid": 1, "ts": 10959137.6953125, "dur": 196718.627929688, "ph": "X", "name": "GenericMethods", "args": { "durationMS": 196.718627929688, "detail": "" } },
{ "pid": 1, "tid": 1, "ts": 11155856.4453125, "dur": 115098.175048828, "ph": "X", "name": "Il2CppTypes", "args": { "durationMS": 115.098175048828, "detail": "" } },
{ "pid": 1, "tid": 1, "ts": 11270956.0546875, "dur": 32735.5461120605, "ph": "X", "name": "GenericMethods", "args": { "durationMS": 32.7355461120605, "detail": "" } },
{ "pid": 1, "tid": 1, "ts": 11303692.3828125, "dur": 105251.235961914, "ph": "X", "name": "CompilerCalculateTypeValues", "args": { "durationMS": 105.251235961914, "detail": "" } },
{ "pid": 1, "tid": 1, "ts": 11408944.3359375, "dur": 2727.99205780029, "ph": "X", "name": "Registration", "args": { "durationMS": 2.72799205780029, "detail": "" } },
{ "pid": 1, "tid": 1, "ts": 11411852.5390625, "dur": 4945.08981704712, "ph": "X", "name": "StringLiteralWriter", "args": { "durationMS": 4.94508981704712, "detail": "" } },
{ "pid": 1, "tid": 1, "ts": 11417072.265625, "dur": 1321.33793830872, "ph": "X", "name": "Metadata Strings", "args": { "durationMS": 1.32133793830872, "detail": "" } },
{ "pid": 1, "tid": 1, "ts": 11418396.484375, "dur": 3789.65306282043, "ph": "X", "name": "Events", "args": { "durationMS": 3.78965306282043, "detail": "" } },
{ "pid": 1, "tid": 1, "ts": 11422186.5234375, "dur": 5021.94690704346, "ph": "X", "name": "Properties", "args": { "durationMS": 5.02194690704346, "detail": "" } },
{ "pid": 1, "tid": 1, "ts": 11427208.984375, "dur": 39078.784942627, "ph": "X", "name": "Methods", "args": { "durationMS": 39.078784942627, "detail": "" } },
{ "pid": 1, "tid": 1, "ts": 11466289.0625, "dur": 961.955964565277, "ph": "X", "name": "Parameter Default Values", "args": { "durationMS": 0.961955964565277, "detail": "" } },
{ "pid": 1, "tid": 1, "ts": 11467250, "dur": 2388.30590248108, "ph": "X", "name": "Field Default Values", "args": { "durationMS": 2.38830590248108, "detail": "" } },
{ "pid": 1, "tid": 1, "ts": 11469640.625, "dur": 436.179995536804, "ph": "X", "name": "Field and Parameter Default Values Data", "args": { "durationMS": 0.436179995536804, "detail": "" } },
{ "pid": 1, "tid": 1, "ts": 11470078.125, "dur": 888.262033462524, "ph": "X", "name": "Field Marshaled Sizes", "args": { "durationMS": 0.888262033462524, "detail": "" } },
{ "pid": 1, "tid": 1, "ts": 11470966.796875, "dur": 14419.4650650024, "ph": "X", "name": "Parameters", "args": { "durationMS": 14.4194650650024, "detail": "" } },
{ "pid": 1, "tid": 1, "ts": 11485386.71875, "dur": 6220.19672393799, "ph": "X", "name": "Fields", "args": { "durationMS": 6.22019672393799, "detail": "" } },
{ "pid": 1, "tid": 1, "ts": 11491607.421875, "dur": 1513.02802562714, "ph": "X", "name": "Generic Parameters", "args": { "durationMS": 1.51302802562714, "detail": "" } },
{ "pid": 1, "tid": 1, "ts": 11493121.09375, "dur": 386.795997619629, "ph": "X", "name": "Generic Parameter Constraints", "args": { "durationMS": 0.386795997619629, "detail": "" } },
{ "pid": 1, "tid": 1, "ts": 11493507.8125, "dur": 1174.2399930954, "ph": "X", "name": "Generic Containers", "args": { "durationMS": 1.1742399930954, "detail": "" } },
{ "pid": 1, "tid": 1, "ts": 11494682.6171875, "dur": 361.606001853943, "ph": "X", "name": "Nested Types", "args": { "durationMS": 0.361606001853943, "detail": "" } },
{ "pid": 1, "tid": 1, "ts": 11495044.921875, "dur": 396.964013576508, "ph": "X", "name": "Interfaces", "args": { "durationMS": 0.396964013576508, "detail": "" } },
{ "pid": 1, "tid": 1, "ts": 11495442.3828125, "dur": 1008.98396968842, "ph": "X", "name": "VTables", "args": { "durationMS": 1.00898396968842, "detail": "" } },
{ "pid": 1, "tid": 1, "ts": 11496452.1484375, "dur": 1679.80802059174, "ph": "X", "name": "Interface Offsets", "args": { "durationMS": 1.67980802059174, "detail": "" } },
{ "pid": 1, "tid": 1, "ts": 11498132.8125, "dur": 33617.3934936523, "ph": "X", "name": "Type Definitions", "args": { "durationMS": 33.6173934936523, "detail": "" } },
{ "pid": 1, "tid": 1, "ts": 11531750, "dur": 4323.38809967041, "ph": "X", "name": "Images", "args": { "durationMS": 4.32338809967041, "detail": "" } },
{ "pid": 1, "tid": 1, "ts": 11536074.21875, "dur": 1942.06297397614, "ph": "X", "name": "Assemblies", "args": { "durationMS": 1.94206297397614, "detail": "" } },
{ "pid": 1, "tid": 1, "ts": 11538017.578125, "dur": 891.883015632629, "ph": "X", "name": "Metadata Usage Lists", "args": { "durationMS": 0.891883015632629, "detail": "" } },
{ "pid": 1, "tid": 1, "ts": 11538910.15625, "dur": 1389.74499702454, "ph": "X", "name": "Metadata Usage Pairs", "args": { "durationMS": 1.38974499702454, "detail": "" } },
{ "pid": 1, "tid": 1, "ts": 11540554.6875, "dur": 411.911994218826, "ph": "X", "name": "Referenced Assemblies", "args": { "durationMS": 0.411911994218826, "detail": "" } },
{ "pid": 1, "tid": 1, "ts": 11540966.796875, "dur": 1310.66989898682, "ph": "X", "name": "Attribute Types Ranges", "args": { "durationMS": 1.31066989898682, "detail": "" } },
{ "pid": 1, "tid": 1, "ts": 11542278.3203125, "dur": 448.750019073486, "ph": "X", "name": "Attribute Types", "args": { "durationMS": 0.448750019073486, "detail": "" } },
{ "pid": 1, "tid": 1, "ts": 11542975.5859375, "dur": 885.295987129211, "ph": "X", "name": "Unresolved Virtual Call Parameter Ranges", "args": { "durationMS": 0.885295987129211, "detail": "" } },
{ "pid": 1, "tid": 1, "ts": 11543860.3515625, "dur": 535.385966300964, "ph": "X", "name": "Windows Runtime type names", "args": { "durationMS": 0.535385966300964, "detail": "" } },
{ "pid": 1, "tid": 1, "ts": 11544397.4609375, "dur": 1453.73594760895, "ph": "X", "name": "Exported Types", "args": { "durationMS": 1.45373594760895, "detail": "" } }
],
"meta_datetime": "10/01/2019 06:34:47",
"meta_command_line_args": "/Applications/Unity/Hub/Editor/2019.1.10f1/Unity.app/Contents/il2cpp/build/il2cppcore/il2cppcore.dll --convert-to-cpp --emit-null-checks --enable-array-bounds-check --dotnetprofile=unityaot --profiler-report --map-file-parser=/Applications/Unity/Hub/Editor/2019.1.10f1/Unity.app/Contents/Tools/MapFileParser/MapFileParser --directory=/Users/kyle/Git/RedYellowGreen/RedYellowGreen/Temp/StagingArea/Data/Managed --generatedcppdir=/Users/kyle/Git/RedYellowGreen/RedYellowGreen/Temp/il2cppOutput/il2cppOutput",
"meta_cpu_count": "4"}
